myrino/__init__.py
myrino/client.py
myrino-1.3.dist-info/LICENSE
myrino-1.3.dist-info/METADATA
myrino-1.3.dist-info/WHEEL
myrino-1.3.dist-info/top_level.txt
myrino-1.3.dist-info/RECORD
