Metadata-Version: 2.1
Name: myrino
Version: 1.3
Summary: myrino is an api-based library for Rubino messengers
Home-page: https://github.com/metect
Author: amirali irvany
Author-email: dev.amirali.irvany@gmail.com
Classifier: Programming Language :: Python :: 3
Classifier: License :: OSI Approved :: MIT License
Requires-Python: >=3.6
License-File: LICENSE
Requires-Dist: requests
